abalin_nameday/__init__.py
abalin_nameday/abalin_nameday.py
abalin_nameday/version.py
abalin_nameday-0.0.4.dist-info/LICENSE
abalin_nameday-0.0.4.dist-info/METADATA
abalin_nameday-0.0.4.dist-info/WHEEL
abalin_nameday-0.0.4.dist-info/top_level.txt
abalin_nameday-0.0.4.dist-info/RECORD
