Metadata-Version: 2.1
Name: abalin-nameday
Version: 0.0.4
Summary: Simple Python wrapper for the International NameDay API @ https://api.abalin.net/
Home-page: https://github.com/viktak/abalin_nameday
Author: @viktak
Author-email: abalin_nameday@viktak.com
License: UNKNOWN
Project-URL: Bug Tracker, https://github.com/viktak/abalin_nameday/issues
Platform: UNKNOWN
Classifier: Programming Language :: Python :: 3
Classifier: License :: OSI Approved :: GNU General Public License v3 (GPLv3)
Classifier: Operating System :: OS Independent
Requires-Python: >=3.7
License-File: LICENSE
